{
  "db_name": "PostgreSQL",
  "query": "\n            SELECT\n                order_id,\n                structure_id,\n                price,\n                remaining,\n                virtual_remaining,\n                type_id\n            FROM market_order_latest mol\n            WHERE mol.type_id = ANY($1)\n            AND mol.structure_id = ANY($2)\n            AND mol.is_buy = false\n            ORDER BY mol.price ASC\n        ",
  "describe": {
    "columns": [
      {
        "ordinal": 0,
        "name": "order_id",
        "type_info": "Int8",
        "origin": {
          "Table": {
            "table": "market_order_latest",
            "name": "order_id"
          }
        }
      },
      {
        "ordinal": 1,
        "name": "structure_id",
        "type_info": "Int8",
        "origin": {
          "Table": {
            "table": "market_order_latest",
            "name": "structure_id"
          }
        }
      },
      {
        "ordinal": 2,
        "name": "price",
        "type_info": "Float8",
        "origin": {
          "Table": {
            "table": "market_order_latest",
            "name": "price"
          }
        }
      },
      {
        "ordinal": 3,
        "name": "remaining",
        "type_info": "Int4",
        "origin": {
          "Table": {
            "table": "market_order_latest",
            "name": "remaining"
          }
        }
      },
      {
        "ordinal": 4,
        "name": "virtual_remaining",
        "type_info": "Int4",
        "origin": {
          "Table": {
            "table": "market_order_latest",
            "name": "virtual_remaining"
          }
        }
      },
      {
        "ordinal": 5,
        "name": "type_id",
        "type_info": "Int4",
        "origin": {
          "Table": {
            "table": "market_order_latest",
            "name": "type_id"
          }
        }
      }
    ],
    "parameters": {
      "Left": [
        "Int4Array",
        "Int8Array"
      ]
    },
    "nullable": [
      false,
      false,
      false,
      false,
      false,
      false
    ]
  },
  "hash": "a0e86e1c24e566c490f9616ad876ab524dcf5c5d78c615f55d085928001326ee"
}
