{
  "db_name": "PostgreSQL",
  "query": "\n            INSERT INTO solution_product\n            (\n                solution_id,\n                type_id,\n                quantity,\n                material_efficiency\n            )\n            SELECT $1, * FROM UNNEST(\n                $2::INTEGER[],\n                $3::INTEGER[],\n                $4::INTEGER[]\n            )\n        ",
  "describe": {
    "columns": [],
    "parameters": {
      "Left": [
        "Uuid",
        "Int4Array",
        "Int4Array",
        "Int4Array"
      ]
    },
    "nullable": []
  },
  "hash": "6500d3ff0ec7641f5c310f78a2cb391ae6d8b393720e05238af47bd36479d450"
}
